stix_shifter_modules/synchronous_dummy/__init__.py
stix_shifter_modules/synchronous_dummy/entry_point.py
stix_shifter_modules/synchronous_dummy/configuration/config.json
stix_shifter_modules/synchronous_dummy/configuration/dialects.json
stix_shifter_modules/synchronous_dummy/configuration/lang_en.json
stix_shifter_modules/synchronous_dummy/stix_translation/__init__.py
stix_shifter_modules/synchronous_dummy/stix_translation/json_to_stix_translator.py
stix_shifter_modules/synchronous_dummy/stix_translation/query_constructor.py
stix_shifter_modules/synchronous_dummy/stix_translation/query_translator.py
stix_shifter_modules/synchronous_dummy/stix_translation/results_translator.py
stix_shifter_modules/synchronous_dummy/stix_translation/json/dialect1_from_stix_map.json
stix_shifter_modules/synchronous_dummy/stix_translation/json/dialect2_from_stix_map.json
stix_shifter_modules/synchronous_dummy/stix_translation/json/operators.json
stix_shifter_modules/synchronous_dummy/stix_translation/json/to_stix_map.json
stix_shifter_modules/synchronous_dummy/stix_transmission/__init__.py
stix_shifter_modules/synchronous_dummy/stix_transmission/api_client.py
stix_shifter_modules/synchronous_dummy/stix_transmission/delete_connector.py
stix_shifter_modules/synchronous_dummy/stix_transmission/error_mapper.py
stix_shifter_modules/synchronous_dummy/stix_transmission/ping_connector.py
stix_shifter_modules/synchronous_dummy/stix_transmission/results_connector.py
stix_shifter_modules_synchronous_dummy-4.0.2.dist-info/LICENSE.md
stix_shifter_modules_synchronous_dummy-4.0.2.dist-info/METADATA
stix_shifter_modules_synchronous_dummy-4.0.2.dist-info/NOTICE
stix_shifter_modules_synchronous_dummy-4.0.2.dist-info/WHEEL
stix_shifter_modules_synchronous_dummy-4.0.2.dist-info/top_level.txt
stix_shifter_modules_synchronous_dummy-4.0.2.dist-info/RECORD
