Metadata-Version: 2.1
Name: stix-shifter-modules-synchronous-dummy
Version: 4.0.2
Summary: Tools and interface to translate STIX formatted results and queries to different data source formats and to set up appropriate connection strings for invoking and triggering actions in openwhisk
Home-page: https://github.com/opencybersecurityalliance/stix-shifter
Author: ibm
Author-email: 
License: UNKNOWN
Project-URL: Source, https://github.com/opencybersecurityalliance/stix-shifter
Keywords: datasource stix translate transform transmit
Platform: UNKNOWN
Classifier: License :: OSI Approved :: Apache Software License
Classifier: Programming Language :: Python :: 3.6
Classifier: Programming Language :: Python :: 3.7
Classifier: Programming Language :: Python :: 3.8
Classifier: Programming Language :: Python :: 3.9
License-File: LICENSE.md
License-File: NOTICE
